madrkit_cli/__init__.py
madrkit_cli/templates/decide-template.md
madrkit_cli/templates/vscode-settings.json
madrkit_cli/templates/commands/decide.md
madrkit-1.0.0.dist-info/METADATA
madrkit-1.0.0.dist-info/WHEEL
madrkit-1.0.0.dist-info/entry_points.txt
madrkit-1.0.0.dist-info/licenses/LICENSE
madrkit-1.0.0.dist-info/RECORD
