Metadata-Version: 2.4
Name: madrkit
Version: 1.0.0
Summary: MADR Kit - A CLI tool for creating and managing Markdown Architecture Decision Records (MADR).
Project-URL: Homepage, https://github.com/mahiguch/madrkit
Project-URL: Repository, https://github.com/mahiguch/madrkit
Project-URL: Issues, https://github.com/mahiguch/madrkit/issues
Project-URL: Documentation, https://github.com/mahiguch/madrkit#readme
Author-email: Masataka Higuchi <mahiguch2@gmail.com>
License: MIT
License-File: LICENSE
Keywords: adr,ai,architecture,cli,decision,madr,records
Classifier: Development Status :: 3 - Alpha
Classifier: Intended Audience :: Developers
Classifier: License :: OSI Approved :: MIT License
Classifier: Operating System :: OS Independent
Classifier: Programming Language :: Python :: 3
Classifier: Programming Language :: Python :: 3.11
Classifier: Programming Language :: Python :: 3.12
Classifier: Topic :: Software Development
Classifier: Topic :: Software Development :: Documentation
Requires-Python: >=3.11
Requires-Dist: httpx[socks]
Requires-Dist: platformdirs
Requires-Dist: readchar
Requires-Dist: rich
Requires-Dist: truststore>=0.10.4
Requires-Dist: typer
